dispatches/__init__.py
dispatches/conftest.py
dispatches/case_studies/__init__.py
dispatches/case_studies/fossil_case/__init__.py
dispatches/case_studies/fossil_case/supercritical_plant/__init__.py
dispatches/case_studies/fossil_case/supercritical_plant/supercritical_powerplant.py
dispatches/case_studies/fossil_case/supercritical_plant/tests/__init__.py
dispatches/case_studies/fossil_case/supercritical_plant/tests/test_scpc_flowsheet.py
dispatches/case_studies/fossil_case/ultra_supercritical_plant/__init__.py
dispatches/case_studies/fossil_case/ultra_supercritical_plant/pfd_ultra_supercritical_pc.svg
dispatches/case_studies/fossil_case/ultra_supercritical_plant/ultra_supercritical_powerplant.py
dispatches/case_studies/fossil_case/ultra_supercritical_plant/storage/__init__.py
dispatches/case_studies/fossil_case/ultra_supercritical_plant/storage/charge_design_ultra_supercritical_power_plant.py
dispatches/case_studies/fossil_case/ultra_supercritical_plant/storage/discharge_design_ultra_supercritical_power_plant.py
dispatches/case_studies/fossil_case/ultra_supercritical_plant/storage/initialized_integrated_storage_usc.json
dispatches/case_studies/fossil_case/ultra_supercritical_plant/storage/integrated_storage_with_ultrasupercritical_power_plant.py
dispatches/case_studies/fossil_case/ultra_supercritical_plant/storage/multiperiod_double_loop_usc.py
dispatches/case_studies/fossil_case/ultra_supercritical_plant/storage/multiperiod_integrated_storage_usc.py
dispatches/case_studies/fossil_case/ultra_supercritical_plant/storage/pricetaker_with_multiperiod_integrated_storage_usc.py
dispatches/case_studies/fossil_case/ultra_supercritical_plant/storage/tests/__init__.py
dispatches/case_studies/fossil_case/ultra_supercritical_plant/storage/tests/test_charge_usc_powerplant.py
dispatches/case_studies/fossil_case/ultra_supercritical_plant/storage/tests/test_discharge_usc_powerplant.py
dispatches-1.2.0.dist-info/LICENSE.md
dispatches-1.2.0.dist-info/METADATA
dispatches-1.2.0.dist-info/WHEEL
dispatches-1.2.0.dist-info/top_level.txt
dispatches-1.2.0.dist-info/RECORD
