Metadata-Version: 2.1
Name: dispatches
Version: 1.2.0
Summary: GMLC DISPATCHES software tools
Home-page: https://github.com/gmlc-dispatches/dispatches
Author: DISPATCHES team
Keywords: market simulation,chemical engineering,process modeling,hybrid power systems
Classifier: Development Status :: 3 - Alpha
Classifier: Intended Audience :: End Users/Desktop
Classifier: Intended Audience :: Science/Research
Classifier: License :: OSI Approved :: BSD License
Classifier: Natural Language :: English
Classifier: Operating System :: MacOS
Classifier: Operating System :: Microsoft :: Windows
Classifier: Operating System :: Unix
Classifier: Programming Language :: Python
Classifier: Programming Language :: Python :: 3
Classifier: Programming Language :: Python :: 3.8
Classifier: Programming Language :: Python :: 3.9
Classifier: Programming Language :: Python :: Implementation :: CPython
Classifier: Topic :: Scientific/Engineering :: Mathematics
Classifier: Topic :: Scientific/Engineering :: Chemistry
Classifier: Topic :: Software Development :: Libraries :: Python Modules
Classifier: Programming Language :: Python :: 3 :: Only
Requires-Python: >=3.8, <4
License-File: LICENSE.md
Requires-Dist: pytest
Requires-Dist: jupyter
Requires-Dist: graphviz
Requires-Dist: gridx-prescient (>=2.2.2)
Requires-Dist: nrel-pysam (>=3.0.1)
Requires-Dist: dispatches-data-packages (>=23.3.19)
Requires-Dist: idaes-pse (==2.0.*)
Provides-Extra: surrogates
Requires-Dist: tslearn (>=0.5.2) ; extra == 'surrogates'
Requires-Dist: tensorflow (>=2.9.1) ; extra == 'surrogates'
Requires-Dist: tables (>=3.6.1) ; extra == 'surrogates'
Requires-Dist: matplotlib ; extra == 'surrogates'
Requires-Dist: dispatches-dynamic-sweep-data (>=23.4.4) ; extra == 'surrogates'
Provides-Extra: teal
Requires-Dist: dispatches-synthetic-price-data (>=23.4.4) ; extra == 'teal'
Requires-Dist: raven-framework (==2.2) ; (python_version <= "3.8" and platform_system != "Linux") and extra == 'teal'
Requires-Dist: teal-ravenframework (==0.3) ; (python_version <= "3.8" and platform_system != "Linux") and extra == 'teal'
